{
	"name": "Minigame2E",
	"events": [
		{
			"eventType": "block",
			"conditions": [
				{
					"id": "on-start-of-layout",
					"objectClass": "System",
					"sid": 242343806944026
				}
			],
			"actions": [
				{
					"id": "pin-to-object-distance",
					"objectClass": "Sprite8",
					"sid": 161804699074235,
					"behaviorType": "Pin",
					"parameters": {
						"pin-to": "Sprite6",
						"mode": "bar-style"
					}
				},
				{
					"id": "set-pin-distance",
					"objectClass": "Sprite8",
					"sid": 850244145325614,
					"behaviorType": "Pin",
					"parameters": {
						"distance": "3"
					}
				},
				{
					"id": "set-angle",
					"objectClass": "Sprite8",
					"sid": 613897622724027,
					"parameters": {
						"angle": "45"
					}
				}
			],
			"sid": 731672291253057
		}
	],
	"sid": 539598816163807
}